satellite_cloud_generator/CloudSimulator.py
satellite_cloud_generator/__init__.py
satellite_cloud_generator/band_magnitudes.py
satellite_cloud_generator/configs.py
satellite_cloud_generator/extras.py
satellite_cloud_generator/noise.py
satellite_cloud_generator/LocalGaussianBlur/LocalGaussianBlur.py
satellite_cloud_generator/LocalGaussianBlur/__init__.py
satellite_cloud_generator/LocalGaussianBlur/src/LocalGaussianBlur.py
satellite_cloud_generator/LocalGaussianBlur/src/__init__.py
satellite_cloud_generator-0.4.dist-info/LICENSE
satellite_cloud_generator-0.4.dist-info/METADATA
satellite_cloud_generator-0.4.dist-info/WHEEL
satellite_cloud_generator-0.4.dist-info/top_level.txt
satellite_cloud_generator-0.4.dist-info/RECORD
